{
    "Ar36": {
        "error": 0.003636519034633236,
        "error_type": "SEM",
        "filter_outliers_dict": {
            "filter_outliers": true,
            "iterations": 2,
            "std_devs": 2
        },
        "fit": "Parabolic",
        "value": 2.8659664203531214
    },
    "Ar37": {
        "error": 0.01640447442390054,
        "error_type": "SEM",
        "filter_outliers_dict": {
            "filter_outliers": true,
            "iterations": 1,
            "std_devs": 3,
            "use_iqr_filtering": false,
            "use_standard_deviation_filtering": false
        },
        "fit": "linear",
        "fn": 339,
        "include_baseline_error": true,
        "n": 340,
        "outlier_excluded": [
            309
        ],
        "reviewed": true,
        "user_excluded": [],
        "value": 1.0847597433218295
    },
    "Ar38": {
        "error": 0.005968589072384085,
        "error_type": "SEM",
        "filter_outliers_dict": {
            "filter_outliers": true,
            "iterations": 1,
            "std_devs": 3,
            "use_iqr_filtering": false,
            "use_standard_deviation_filtering": false
        },
        "fit": "linear",
        "fn": 338,
        "include_baseline_error": true,
        "n": 340,
        "outlier_excluded": [
            144,
            254
        ],
        "reviewed": true,
        "user_excluded": [],
        "value": 2.3305683107951665
    },
    "Ar39": {
        "error": 0.008930551654468454,
        "error_type": "SEM",
        "filter_outliers_dict": {
            "filter_outliers": true,
            "iterations": 1,
            "std_devs": 3,
            "use_iqr_filtering": false,
            "use_standard_deviation_filtering": false
        },
        "fit": "linear",
        "fn": 339,
        "include_baseline_error": true,
        "n": 340,
        "outlier_excluded": [
            162
        ],
        "reviewed": true,
        "user_excluded": [],
        "value": 20.70676891728941
    },
    "Ar40": {
        "error": 0.08565585651374436,
        "error_type": "SEM",
        "filter_outliers_dict": {
            "filter_outliers": true,
            "iterations": 1,
            "std_devs": 3,
            "use_iqr_filtering": false,
            "use_standard_deviation_filtering": false
        },
        "fit": "parabolic",
        "fn": 337,
        "include_baseline_error": true,
        "n": 340,
        "outlier_excluded": [
            120,
            278,
            279
        ],
        "reviewed": true,
        "user_excluded": [],
        "value": 845.7522233849135
    }
}